setup.py
dataqualityhdfs/__init__.py
dataqualityhdfs.egg-info/PKG-INFO
dataqualityhdfs.egg-info/SOURCES.txt
dataqualityhdfs.egg-info/dependency_links.txt
dataqualityhdfs.egg-info/requires.txt
dataqualityhdfs.egg-info/top_level.txt
dataqualityhdfs/configs/__init__.py
dataqualityhdfs/core/__init__.py
dataqualityhdfs/core/column.py
dataqualityhdfs/core/enum_type.py
dataqualityhdfs/core/interface.py
dataqualityhdfs/core/table.py
dataqualityhdfs/core/granularity/__init__.py
dataqualityhdfs/core/granularity/granularity.py
dataqualityhdfs/core/granularity/granularitytemporal.py
dataqualityhdfs/core/granularity/granularitytimeinterval.py
dataqualityhdfs/metrics/__init__.py
dataqualityhdfs/metrics/metric.py
dataqualityhdfs/metrics/metriccolumn.py
dataqualityhdfs/metrics/metriccontext.py
dataqualityhdfs/metrics/metricfile.py
dataqualityhdfs/metrics/metricservice.py
dataqualityhdfs/metrics/metricexpressions/__init__.py
dataqualityhdfs/metrics/metricexpressions/metricexpression.py
dataqualityhdfs/metrics/metricexpressions/metricexpressionnullvalue.py
dataqualityhdfs/metrics/metricresult/__init__.py
dataqualityhdfs/metrics/metricresult/metricresult.py
dataqualityhdfs/metrics/metricresult/metricresultagg.py
dataqualityhdfs/metrics/metricresult/metricresultvalidation.py
dataqualityhdfs/source/__init__.py
dataqualityhdfs/source/source.py
dataqualityhdfs/source/sourcebbdd/__init__.py
dataqualityhdfs/source/sourcebbdd/sourcehive.py
dataqualityhdfs/source/sourcefile/__init__.py
dataqualityhdfs/source/sourcefile/sourcecsv.py
dataqualityhdfs/source/sourcefile/sourcefile.py
dataqualityhdfs/test/__init__.py
dataqualityhdfs/test/test.py
dataqualityhdfs/test/testresult.py
dataqualityhdfs/test/testservice.py
dataqualityhdfs/test/testoperations/__init__.py
dataqualityhdfs/test/testoperations/testoperation.py
dataqualityhdfs/test/testoperations/testoperationmayor.py
dataqualityhdfs/test/testoperations/testoperationminor.py
dataqualityhdfs/test/testrepresentations/__init__.py
dataqualityhdfs/test/testrepresentations/testrepresentation.py
dataqualityhdfs/test/testrepresentations/testrepresentationpercentage.py
dataqualityhdfs/test/testrepresentations/testtepresentationvalue.py