Metadata-Version: 1.1
Name: dataqualityhdfs
Version: 1.0.0
Summary: A DataQualityHDFS Python project
Home-page: https://github.com/LucumaTeam/DataQualityHDFS
Author: UNKNOWN
Author-email: UNKNOWN
License: UNKNOWN
Platform: UNKNOWN
Classifier: Development Status :: 3 - Alpha
Classifier: Intended Audience :: Developers
Classifier: Topic :: Software Development :: Build Tools
Classifier: License :: OSI Approved :: MIT License
Classifier: Programming Language :: Python :: 2.7
